Metadata-Version: 2.1
Name: calculator-2022
Version: 0.1
Summary: Calculator performs: Addition / Subtraction, Multiplication / Division, Take (n) root of a number
Home-page: UNKNOWN
Author: Gabija Gedvilaite
Author-email: gabija_g@hotmail.com
License: UNKNOWN
Platform: UNKNOWN
Classifier: Programming Language :: Python
Classifier: License :: OSI Approved :: MIT License
Classifier: Operating System :: OS Independent
